bm_api_dev/Project.py
bm_api_dev/User.py
bm_api_dev/__init__.py
bm_api_dev-0.2.1.dist-info/LICENSE
bm_api_dev-0.2.1.dist-info/METADATA
bm_api_dev-0.2.1.dist-info/WHEEL
bm_api_dev-0.2.1.dist-info/top_level.txt
bm_api_dev-0.2.1.dist-info/RECORD
