Metadata-Version: 2.1
Name: bm_api_dev
Version: 0.2.1
Summary: This is a test helper package for Beyond Monitoring API
Home-page: https://github.com/Sixense-Data-Manager/bm_api_dev
Author: Kan-Jen Liu
Author-email: kanjen.liu@sixense-group.com
Classifier: Programming Language :: Python :: 3
Classifier: License :: OSI Approved :: MIT License
Classifier: Operating System :: OS Independent
Requires-Python: >=3.6
License-File: LICENSE
